{"cameraMode":{"drawMode":0,"name":"Shaded","section":"Shading Mode"},"sceneLighting":false,"audioPlay":false,"sceneViewState":{"showFog":true,"showMaterialUpdate":false,"showSkybox":false,"showFlares":true,"showImageEffects":true,"showParticleSystems":true},"in2DMode":false,"pivot":{"x":-16.484905242919923,"y":-0.5058341026306152,"z":3.242926597595215},"rotation":{"x":0.05881604179739952,"y":-0.9318426847457886,"z":0.17565107345581056,"w":0.31202027201652529},"size":19.470657348632814,"orthographic":false}