{"cameraMode":{"drawMode":0,"name":"Shaded","section":"Shading Mode"},"sceneLighting":false,"audioPlay":false,"sceneViewState":{"showFog":true,"showMaterialUpdate":false,"showSkybox":false,"showFlares":true,"showImageEffects":true,"showParticleSystems":true},"in2DMode":false,"pivot":{"x":0.7484089136123657,"y":2.813350200653076,"z":-1.8846114873886109},"rotation":{"x":-0.12036091089248657,"y":-0.7339462637901306,"z":0.13493075966835023,"w":-0.654698371887207},"size":7.8561482429504398,"orthographic":false}